cycleosmdata/__init__.py
cycleosmdata/bikeosm.py
cycleosmdata/pbfdownloader.py
cycleosmdata/utils.py
cycleosmdata/static/general - states.csv
cycleosmdata/static/geofabrik - Sept2024.csv
cycleosmdata/static/geofabrik - latest.csv
cycleosmdata/static/geofabrik - test.csv
cycleosmdata/static/osm_links - cycleways.txt
cycleosmdata/static/osm_links - fclasses.txt
cycleosmdata/static/osm_links - not_bikelanes.txt
cycleosmdata/static/osm_links - tags.csv
cycleosmdata-0.0.2.4.dist-info/METADATA
cycleosmdata-0.0.2.4.dist-info/WHEEL
cycleosmdata-0.0.2.4.dist-info/licenses/LICENSE
cycleosmdata-0.0.2.4.dist-info/RECORD
