Metadata-Version: 2.3
Name: cycleosmdata
Version: 0.0.2.4
Summary: A small package to download structured bike infrastructure data from Open Street Map (OSM).
Project-URL: homepage, https://github.com/Bikingman/cycleosmdata
Project-URL: documentation, https://github.com/Bikingman/cycleosmdata
Project-URL: repository, https://github.com/Bikingman/cycleosmdata
Project-URL: Bug Tracker, https://github.com/Bikingman/cycleosmdata/issues
Author-email: Daniel Patterson <dpatterson@geoinformatics.studio>
Classifier: Environment :: Console
Classifier: License :: OSI Approved :: MIT License
Classifier: Operating System :: OS Independent
Classifier: Programming Language :: Python
Classifier: Programming Language :: Python :: 3
Classifier: Programming Language :: Python :: 3 :: Only
Requires-Python: >=3.7
